final_results/verification/fir_diagnostic.v
`timescale 1ns/1ns

module fir_diagnostic(

    input [3:0] h0,
    input [3:0] h1,
    input [3:0] h2,
    input [3:0] h3,

    input [3:0] x0,
    input [3:0] x1,
    input [3:0] x2,
    input [3:0] x3,

    input [7:0] p0,
    input [7:0] p1,
    input [7:0] p2,
    input [7:0] p3,

    output fault_p0,
    output fault_p1,
    output fault_p2,
    output fault_p3,

    output [3:0] fault_vector,

    output fault_detected,
    output [1:0] fault_location,
    output [2:0] fault_bit,
    output fault_type

);

wire [7:0] expected_p0;
wire [7:0] expected_p1;
wire [7:0] expected_p2;
wire [7:0] expected_p3;

wire [7:0] mismatch_p0;
wire [7:0] mismatch_p1;
wire [7:0] mismatch_p2;
wire [7:0] mismatch_p3;

wire [7:0] selected_expected;
wire selected_actual;


assign expected_p0 = h0 * x0;
assign expected_p1 = h1 * x1;
assign expected_p2 = h2 * x2;
assign expected_p3 = h3 * x3;


assign mismatch_p0 = expected_p0 ^ p0;
assign mismatch_p1 = expected_p1 ^ p1;
assign mismatch_p2 = expected_p2 ^ p2;
assign mismatch_p3 = expected_p3 ^ p3;


assign fault_p0 = |mismatch_p0;
assign fault_p1 = |mismatch_p1;
assign fault_p2 = |mismatch_p2;
assign fault_p3 = |mismatch_p3;


assign fault_vector = {
    fault_p3,
    fault_p2,
    fault_p1,
    fault_p0
};


assign fault_detected =
        fault_p0 |
        fault_p1 |
        fault_p2 |
        fault_p3;


assign fault_location =
        fault_p0 ? 2'b00 :
        fault_p1 ? 2'b01 :
        fault_p2 ? 2'b10 :
        fault_p3 ? 2'b11 :
                   2'b00;


assign fault_bit =
        fault_p0 ? (
            mismatch_p0[0] ? 3'd0 :
            mismatch_p0[1] ? 3'd1 :
            mismatch_p0[2] ? 3'd2 :
            mismatch_p0[3] ? 3'd3 :
            mismatch_p0[4] ? 3'd4 :
            mismatch_p0[5] ? 3'd5 :
            mismatch_p0[6] ? 3'd6 :
            mismatch_p0[7] ? 3'd7 :
            3'd0
        ) :
        fault_p1 ? (
            mismatch_p1[0] ? 3'd0 :
            mismatch_p1[1] ? 3'd1 :
            mismatch_p1[2] ? 3'd2 :
            mismatch_p1[3] ? 3'd3 :
            mismatch_p1[4] ? 3'd4 :
            mismatch_p1[5] ? 3'd5 :
            mismatch_p1[6] ? 3'd6 :
            mismatch_p1[7] ? 3'd7 :
            3'd0
        ) :
        fault_p2 ? (
            mismatch_p2[0] ? 3'd0 :
            mismatch_p2[1] ? 3'd1 :
            mismatch_p2[2] ? 3'd2 :
            mismatch_p2[3] ? 3'd3 :
            mismatch_p2[4] ? 3'd4 :
            mismatch_p2[5] ? 3'd5 :
            mismatch_p2[6] ? 3'd6 :
            mismatch_p2[7] ? 3'd7 :
            3'd0
        ) :
        fault_p3 ? (
            mismatch_p3[0] ? 3'd0 :
            mismatch_p3[1] ? 3'd1 :
            mismatch_p3[2] ? 3'd2 :
            mismatch_p3[3] ? 3'd3 :
            mismatch_p3[4] ? 3'd4 :
            mismatch_p3[5] ? 3'd5 :
            mismatch_p3[6] ? 3'd6 :
            mismatch_p3[7] ? 3'd7 :
            3'd0
        ) :
        3'd0;


assign selected_expected =
        fault_p0 ? expected_p0 :
        fault_p1 ? expected_p1 :
        fault_p2 ? expected_p2 :
        fault_p3 ? expected_p3 :
        8'd0;


assign selected_actual =
        fault_p0 ? p0[fault_bit] :
        fault_p1 ? p1[fault_bit] :
        fault_p2 ? p2[fault_bit] :
        fault_p3 ? p3[fault_bit] :
        1'b0;


assign fault_type =
        fault_detected ?
        ((selected_expected[fault_bit] == 1'b0) &&
         (selected_actual == 1'b1)) :
        1'b0;

endmodule

rtl/fir.v
`timescale 1ns/1ns

module fir(

    input [3:0] x,
    input [3:0] h0,
    input [3:0] h1,
    input [3:0] h2,
    input [3:0] h3,

    input rst,
    input clk,

    output [9:0] y,

    output [3:0] x0,
    output [3:0] x1,
    output [3:0] x2,
    output [3:0] x3,

    output [7:0] p0,
    output [7:0] p1,
    output [7:0] p2,
    output [7:0] p3

);

reg [3:0] x0_reg;
reg [3:0] x1_reg;
reg [3:0] x2_reg;
reg [3:0] x3_reg;

assign x0 = x0_reg;
assign x1 = x1_reg;
assign x2 = x2_reg;
assign x3 = x3_reg;

assign p0 = h0 * x0_reg;
assign p1 = h1 * x1_reg;
assign p2 = h2 * x2_reg;
assign p3 = h3 * x3_reg;

assign y = p0 + p1 + p2 + p3;

always @(posedge clk) begin

    if (rst) begin

        x0_reg <= 4'd0;
        x1_reg <= 4'd0;
        x2_reg <= 4'd0;
        x3_reg <= 4'd0;

    end

    else begin

        x0_reg <= x;
        x1_reg <= x0_reg;
        x2_reg <= x1_reg;
        x3_reg <= x2_reg;

    end

end

endmodule

final_results/verification/diagnostic_controller.v
`timescale 1ns/1ns

module diagnostic_controller(

    input clk,
    input rst,
    input start_diag,

    output reg [3:0] test_x,
    output reg diag_busy,
    output reg diag_done

);

reg [3:0] state;

localparam IDLE      = 4'd0;
localparam TEST1     = 4'd1;
localparam WAIT1     = 4'd2;
localparam TEST2     = 4'd3;
localparam WAIT2     = 4'd4;
localparam TEST3     = 4'd5;
localparam WAIT3     = 4'd6;
localparam TEST4     = 4'd7;
localparam WAIT4     = 4'd8;
localparam TEST5     = 4'd9;
localparam WAIT5     = 4'd10;
localparam DONE      = 4'd11;


always @(posedge clk) begin

    if (rst) begin

        state <= IDLE;

        test_x <= 4'd0;

        diag_busy <= 1'b0;
        diag_done <= 1'b0;

    end

    else begin

        diag_done <= 1'b0;

        case (state)

            IDLE: begin

                test_x <= 4'd0;
                diag_busy <= 1'b0;

                if (start_diag) begin

                    state <= TEST1;
                    diag_busy <= 1'b1;

                end

            end


            TEST1: begin

                test_x <= 4'd1;

                state <= WAIT1;

            end


            WAIT1: begin

                test_x <= 4'd1;

                state <= TEST2;

            end


            TEST2: begin

                test_x <= 4'd2;

                state <= WAIT2;

            end


            WAIT2: begin

                test_x <= 4'd2;

                state <= TEST3;

            end


            TEST3: begin

                test_x <= 4'd3;

                state <= WAIT3;

            end


            WAIT3: begin

                test_x <= 4'd3;

                state <= TEST4;

            end


            TEST4: begin

                test_x <= 4'd4;

                state <= WAIT4;

            end


            WAIT4: begin

                test_x <= 4'd4;

                state <= TEST5;

            end


            TEST5: begin

                test_x <= 4'd7;

                state <= WAIT5;

            end


            WAIT5: begin

                test_x <= 4'd7;

                state <= DONE;

            end


            DONE: begin

                test_x <= 4'd0;

                diag_busy <= 1'b0;
                diag_done <= 1'b1;

                state <= IDLE;

            end


            default: begin

                state <= IDLE;

                test_x <= 4'd0;

                diag_busy <= 1'b0;
                diag_done <= 1'b0;

            end

        endcase

    end

end

endmodule

final_results/verification/self_diagnosing_fir.v
`timescale 1ns/1ns

module self_diagnosing_fir(
    input [3:0] x,

    input [3:0] h0,
    input [3:0] h1,
    input [3:0] h2,
    input [3:0] h3,

    input rst,
    input clk,

    input start_diag,

    output [9:0] y,

    output fault_detected,
    output [1:0] fault_location,
    output [2:0] fault_bit,
    output fault_type,
    output [3:0] fault_vector,

    output diag_busy,
    output diag_done
);

wire [3:0] test_x;
wire [3:0] fir_x;

wire [3:0] x0;
wire [3:0] x1;
wire [3:0] x2;
wire [3:0] x3;

wire [7:0] p0;
wire [7:0] p1;
wire [7:0] p2;
wire [7:0] p3;

wire fault_detected_live;
wire [1:0] fault_location_live;
wire [2:0] fault_bit_live;
wire fault_type_live;
wire [3:0] fault_vector_live;

reg fault_detected_reg;
reg [1:0] fault_location_reg;
reg [2:0] fault_bit_reg;
reg fault_type_reg;
reg [3:0] fault_vector_reg;

reg diag_done_d;


assign fir_x = diag_busy ? test_x : x;


diagnostic_controller controller(
    .clk(clk),
    .rst(rst),
    .start_diag(start_diag),
    .test_x(test_x),
    .diag_busy(diag_busy),
    .diag_done(diag_done)
);


fir fir_core(
    .x(fir_x),
    .h0(h0),
    .h1(h1),
    .h2(h2),
    .h3(h3),
    .rst(rst),
    .clk(clk),
    .y(y),
    .x0(x0),
    .x1(x1),
    .x2(x2),
    .x3(x3),
    .p0(p0),
    .p1(p1),
    .p2(p2),
    .p3(p3)
);


fir_diagnostic diagnostic(
    .h0(h0),
    .h1(h1),
    .h2(h2),
    .h3(h3),

    .x0(x0),
    .x1(x1),
    .x2(x2),
    .x3(x3),

    .p0(p0),
    .p1(p1),
    .p2(p2),
    .p3(p3),

    .fault_p0(),
    .fault_p1(),
    .fault_p2(),
    .fault_p3(),

    .fault_vector(fault_vector_live),

    .fault_detected(fault_detected_live),
    .fault_location(fault_location_live),
    .fault_bit(fault_bit_live),
    .fault_type(fault_type_live)
);


always @(posedge clk) begin

    if (rst) begin

        fault_detected_reg <= 1'b0;
        fault_location_reg <= 2'b00;
        fault_bit_reg <= 3'd0;
        fault_type_reg <= 1'b0;
        fault_vector_reg <= 4'b0000;

        diag_done_d <= 1'b0;

    end

    else begin

        diag_done_d <= diag_done;

        if (diag_done_d) begin

            fault_detected_reg <= fault_detected_live;
            fault_location_reg <= fault_location_live;
            fault_bit_reg <= fault_bit_live;
            fault_type_reg <= fault_type_live;
            fault_vector_reg <= fault_vector_live;

        end

    end

end


assign fault_detected = fault_detected_reg;
assign fault_location = fault_location_reg;
assign fault_bit = fault_bit_reg;
assign fault_type = fault_type_reg;
assign fault_vector = fault_vector_reg;

endmodule

final_results/verification/self_diagnosing_fault_tb.v
`timescale 1ns/1ns

module self_diagnosing_fault_tb;

reg [3:0] x;

reg [3:0] h0;
reg [3:0] h1;
reg [3:0] h2;
reg [3:0] h3;

reg rst;
reg clk;
reg start_diag;

reg [1:0] fault_location;
reg [2:0] fault_bit;
reg [1:0] fault_type;

wire [9:0] y;

wire fault_detected;
wire [1:0] detected_location;
wire [2:0] detected_bit;
wire detected_fault_type;
wire [3:0] fault_vector;

wire diag_busy;
wire diag_done;


self_diagnosing_fir dut(

    .x(x),

    .h0(h0),
    .h1(h1),
    .h2(h2),
    .h3(h3),

    .rst(rst),
    .clk(clk),

    .start_diag(start_diag),

    .y(y),

    .fault_detected(fault_detected),
    .fault_location(detected_location),
    .fault_bit(detected_bit),
    .fault_type(detected_fault_type),
    .fault_vector(fault_vector),

    .diag_busy(diag_busy),
    .diag_done(diag_done)

);


initial begin
    clk = 0;
    forever #50 clk = ~clk;
end


initial begin

    $dumpfile("simulation/complete_self_diagnosis.vcd");
    $dumpvars(0, self_diagnosing_fault_tb);

    h0 = 4'd15;
    h1 = 4'd13;
    h2 = 4'd11;
    h3 = 4'd9;

    x = 4'd0;

    rst = 1;
    start_diag = 0;

    fault_location = 2'b00;
    fault_bit = 3'd0;
    fault_type = 2'b00;

    #100;

    rst = 0;

    #100;


    // ========================================
    // TEST 1
    // HEALTHY SELF-DIAGNOSIS
    // ========================================

    x = 4'd1;

    start_diag = 1;

    #100;

    start_diag = 0;

    wait(diag_done);

    #10;

    if ((fault_detected == 1'b0) &&
        (fault_vector == 4'b0000))

        $display("PASS | HEALTHY | vector=%b | diagnostic complete",
                 fault_vector);

    else

        $display("FAIL | HEALTHY | vector=%b",
                 fault_vector);


    #100;


    // ========================================
    // TEST 2
    // p0 bit 0 stuck-at-0
    // ========================================

    force dut.p0[0] = 1'b0;

    x = 4'd1;

    start_diag = 1;

    #100;

    start_diag = 0;

    wait(diag_done);

    #10;

    if ((fault_detected == 1'b1) &&
        (detected_location == 2'b00) &&
        (detected_bit == 3'd0) &&
        (detected_fault_type == 1'b0) &&
        (fault_vector == 4'b0001))

        $display("PASS | p0 bit 0 stuck-at-0 | vector=%b | location=%b | bit=%d",
                 fault_vector,
                 detected_location,
                 detected_bit);

    else

        $display("FAIL | p0 bit 0 stuck-at-0 | vector=%b | location=%b | bit=%d",
                 fault_vector,
                 detected_location,
                 detected_bit);

    release dut.p0[0];

    #100;


    // ========================================
    // TEST 3
    // p2 bit 3 stuck-at-0
    // ========================================

    force dut.p2[3] = 1'b0;

    x = 4'd1;

    start_diag = 1;

    #100;

    start_diag = 0;

    wait(diag_done);

    #10;

    if ((fault_detected == 1'b1) &&
        (detected_location == 2'b10) &&
        (detected_bit == 3'd3) &&
        (detected_fault_type == 1'b0) &&
        (fault_vector == 4'b0100))

        $display("PASS | p2 bit 3 stuck-at-0 | vector=%b | location=%b | bit=%d",
                 fault_vector,
                 detected_location,
                 detected_bit);

    else

        $display("FAIL | p2 bit 3 stuck-at-0 | vector=%b | location=%b | bit=%d",
                 fault_vector,
                 detected_location,
                 detected_bit);

    release dut.p2[3];

    #100;


    // ========================================
    // TEST 4
    // p1 bit 7 stuck-at-1
    // ========================================

    force dut.p1[7] = 1'b1;

    x = 4'd1;

    start_diag = 1;

    #100;

    start_diag = 0;

    wait(diag_done);

    #10;

    if ((fault_detected == 1'b1) &&
        (detected_location == 2'b01) &&
        (detected_bit == 3'd7) &&
        (detected_fault_type == 1'b1) &&
        (fault_vector == 4'b0010))

        $display("PASS | p1 bit 7 stuck-at-1 | vector=%b | location=%b | bit=%d",
                 fault_vector,
                 detected_location,
                 detected_bit);

    else

        $display("FAIL | p1 bit 7 stuck-at-1 | vector=%b | location=%b | bit=%d",
                 fault_vector,
                 detected_location,
                 detected_bit);

    release dut.p1[7];

    #100;


    // ========================================
    // TEST 5
    // p3 bit 6 stuck-at-1
    // ========================================

    force dut.p3[6] = 1'b1;

    x = 4'd1;

    start_diag = 1;

    #100;

    start_diag = 0;

    wait(diag_done);

    #10;

    if ((fault_detected == 1'b1) &&
        (detected_location == 2'b11) &&
        (detected_bit == 3'd6) &&
        (detected_fault_type == 1'b1) &&
        (fault_vector == 4'b1000))

        $display("PASS | p3 bit 6 stuck-at-1 | vector=%b | location=%b | bit=%d",
                 fault_vector,
                 detected_location,
                 detected_bit);

    else

        $display("FAIL | p3 bit 6 stuck-at-1 | vector=%b | location=%b | bit=%d",
                 fault_vector,
                 detected_location,
                 detected_bit);

    release dut.p3[6];


    // ========================================
    // COMPLETE
    // ========================================

    $display("");
    $display("==============================================");
    $display(" COMPLETE SELF-DIAGNOSIS TEST COMPLETE");
    $display("==============================================");

    $finish;

end

endmodule

simulation/complete_self_diagnosis.vcd
$date
	Sat Sep 19 15:02:08 2026
$end
$version
	Icarus Verilog
$end
$timescale
	1ns
$end
$scope module self_diagnosing_fault_tb $end
$var wire 10 ! y [9:0] $end
$var wire 4 " fault_vector [3:0] $end
$var wire 1 # fault_detected $end
$var wire 1 $ diag_done $end
$var wire 1 % diag_busy $end
$var wire 2 & detected_location [1:0] $end
$var wire 1 ' detected_fault_type $end
$var wire 3 ( detected_bit [2:0] $end
$var reg 1 ) clk $end
$var reg 3 * fault_bit [2:0] $end
$var reg 2 + fault_location [1:0] $end
$var reg 2 , fault_type [1:0] $end
$var reg 4 - h0 [3:0] $end
$var reg 4 . h1 [3:0] $end
$var reg 4 / h2 [3:0] $end
$var reg 4 0 h3 [3:0] $end
$var reg 1 1 rst $end
$var reg 1 2 start_diag $end
$var reg 4 3 x [3:0] $end
$scope module dut $end
$var wire 1 ) clk $end
$var wire 3 4 fault_bit [2:0] $end
$var wire 1 # fault_detected $end
$var wire 2 5 fault_location [1:0] $end
$var wire 1 ' fault_type $end
$var wire 4 6 fault_vector [3:0] $end
$var wire 4 7 h0 [3:0] $end
$var wire 4 8 h1 [3:0] $end
$var wire 4 9 h2 [3:0] $end
$var wire 4 : h3 [3:0] $end
$var wire 1 1 rst $end
$var wire 1 2 start_diag $end
$var wire 4 ; x [3:0] $end
$var wire 10 < y [9:0] $end
$var wire 4 = x3 [3:0] $end
$var wire 4 > x2 [3:0] $end
$var wire 4 ? x1 [3:0] $end
$var wire 4 @ x0 [3:0] $end
$var wire 4 A test_x [3:0] $end
$var wire 8 B p3 [7:0] $end
$var wire 8 C p2 [7:0] $end
$var wire 8 D p1 [7:0] $end
$var wire 8 E p0 [7:0] $end
$var wire 4 F fir_x [3:0] $end
$var wire 4 G fault_vector_live [3:0] $end
$var wire 1 H fault_type_live $end
$var wire 2 I fault_location_live [1:0] $end
$var wire 1 J fault_detected_live $end
$var wire 3 K fault_bit_live [2:0] $end
$var wire 1 $ diag_done $end
$var wire 1 % diag_busy $end
$var reg 1 L diag_done_d $end
$var reg 3 M fault_bit_reg [2:0] $end
$var reg 1 N fault_detected_reg $end
$var reg 2 O fault_location_reg [1:0] $end
$var reg 1 P fault_type_reg $end
$var reg 4 Q fault_vector_reg [3:0] $end
$scope module controller $end
$var wire 1 ) clk $end
$var wire 1 1 rst $end
$var wire 1 2 start_diag $end
$var parameter 4 R DONE $end
$var parameter 4 S IDLE $end
$var parameter 4 T TEST1 $end
$var parameter 4 U TEST2 $end
$var parameter 4 V TEST3 $end
$var parameter 4 W TEST4 $end
$var parameter 4 X TEST5 $end
$var parameter 4 Y WAIT1 $end
$var parameter 4 Z WAIT2 $end
$var parameter 4 [ WAIT3 $end
$var parameter 4 \ WAIT4 $end
$var parameter 4 ] WAIT5 $end
$var reg 1 % diag_busy $end
$var reg 1 $ diag_done $end
$var reg 4 ^ state [3:0] $end
$var reg 4 _ test_x [3:0] $end
$upscope $end
$scope module diagnostic $end
$var wire 1 J fault_detected $end
$var wire 4 ` h0 [3:0] $end
$var wire 4 a h1 [3:0] $end
$var wire 4 b h2 [3:0] $end
$var wire 4 c h3 [3:0] $end
$var wire 8 d mismatch_p0 [7:0] $end
$var wire 8 e mismatch_p1 [7:0] $end
$var wire 8 f mismatch_p2 [7:0] $end
$var wire 8 g mismatch_p3 [7:0] $end
$var wire 4 h x3 [3:0] $end
$var wire 4 i x2 [3:0] $end
$var wire 4 j x1 [3:0] $end
$var wire 4 k x0 [3:0] $end
$var wire 8 l selected_expected [7:0] $end
$var wire 1 m selected_actual $end
$var wire 8 n p3 [7:0] $end
$var wire 8 o p2 [7:0] $end
$var wire 8 p p1 [7:0] $end
$var wire 8 q p0 [7:0] $end
$var wire 4 r fault_vector [3:0] $end
$var wire 1 H fault_type $end
$var wire 1 s fault_p3 $end
$var wire 1 t fault_p2 $end
$var wire 1 u fault_p1 $end
$var wire 1 v fault_p0 $end
$var wire 2 w fault_location [1:0] $end
$var wire 3 x fault_bit [2:0] $end
$var wire 8 y expected_p3 [7:0] $end
$var wire 8 z expected_p2 [7:0] $end
$var wire 8 { expected_p1 [7:0] $end
$var wire 8 | expected_p0 [7:0] $end
$upscope $end
$scope module fir_core $end
$var wire 1 ) clk $end
$var wire 4 } h0 [3:0] $end
$var wire 4 ~ h1 [3:0] $end
$var wire 4 !" h2 [3:0] $end
$var wire 4 "" h3 [3:0] $end
$var wire 1 1 rst $end
$var wire 4 #" x [3:0] $end
$var wire 4 $" x0 [3:0] $end
$var wire 4 %" x1 [3:0] $end
$var wire 4 &" x2 [3:0] $end
$var wire 4 '" x3 [3:0] $end
$var wire 10 (" y [9:0] $end
$var wire 8 )" p3 [7:0] $end
$var wire 8 *" p2 [7:0] $end
$var wire 8 +" p1 [7:0] $end
$var wire 8 ," p0 [7:0] $end
$var reg 4 -" x0_reg [3:0] $end
$var reg 4 ." x1_reg [3:0] $end
$var reg 4 /" x2_reg [3:0] $end
$var reg 4 0" x3_reg [3:0] $end
$upscope $end
$upscope $end
$upscope $end
$enddefinitions $end
$comment Show the parameter values. $end
$dumpall
b1010 ]
b1000 \
b110 [
b100 Z
b10 Y
b1001 X
b111 W
b101 V
b11 U
b1 T
b0 S
b1011 R
$end
#0
$dumpvars
bx 0"
bx /"
bx ."
bx -"
bx ,"
bx +"
bx *"
bx )"
bx ("
bx '"
bx &"
bx %"
bx $"
bx #"
b1001 ""
b1011 !"
b1101 ~
b1111 }
bx |
bx {
bx z
bx y
bx x
bx w
xv
xu
xt
xs
bx r
bx q
bx p
bx o
bx n
xm
bx l
bx k
bx j
bx i
bx h
bx g
bx f
bx e
bx d
b1001 c
b1011 b
b1101 a
b1111 `
bx _
bx ^
bx Q
xP
bx O
xN
bx M
xL
bx K
xJ
bx I
xH
bx G
bx F
bx E
bx D
bx C
bx B
bx A
bx @
bx ?
bx >
bx =
bx <
b0 ;
b1001 :
b1011 9
b1101 8
b1111 7
bx 6
bx 5
bx 4
b0 3
02
11
b1001 0
b1011 /
b1101 .
b1111 -
b0 ,
b0 +
b0 *
0)
bx (
x'
bx &
x%
x$
x#
bx "
bx !
$end
#50
b0 I
b0 w
b0 K
b0 x
0m
b0 l
0H
0J
b0 G
b0 r
b0 !
b0 <
b0 ("
0s
b0 g
0t
b0 f
0u
b0 e
0v
b0 d
b0 F
b0 #"
b0 B
b0 n
b0 )"
b0 y
b0 C
b0 o
b0 *"
b0 z
b0 D
b0 p
b0 +"
b0 {
b0 E
b0 q
b0 ,"
b0 |
0$
0%
b0 A
b0 _
b0 ^
b0 =
b0 h
b0 '"
b0 0"
b0 >
b0 i
b0 &"
b0 /"
b0 ?
b0 j
b0 %"
b0 ."
b0 @
b0 k
b0 $"
b0 -"
0L
b0 "
b0 6
b0 Q
0'
0P
b0 (
b0 4
b0 M
b0 &
b0 5
b0 O
0#
0N
1)
#100
0)
01
#150
1)
#200
b1 F
b1 #"
0)
12
b1 3
b1 ;
#250
b1111 !
b1111 <
b1111 ("
b0 F
b0 #"
b1111 E
b1111 q
b1111 ,"
b1111 |
1%
b1 ^
b1 @
b1 k
b1 $"
b1 -"
1)
#300
0)
02
#350
b1101 !
b1101 <
b1101 ("
b1101 D
b1101 p
b1101 +"
b1101 {
b0 E
b0 q
b0 ,"
b0 |
b1 F
b1 #"
b1 ?
b1 j
b1 %"
b1 ."
b0 @
b0 k
b0 $"
b0 -"
b10 ^
b1 A
b1 _
1)
#400
0)
#450
b11010 !
b11010 <
b11010 ("
b1011 C
b1011 o
b1011 *"
b1011 z
b0 D
b0 p
b0 +"
b0 {
b1111 E
b1111 q
b1111 ,"
b1111 |
b11 ^
b1 >
b1 i
b1 &"
b1 /"
b0 ?
b0 j
b0 %"
b0 ."
b1 @
b1 k
b1 $"
b1 -"
1)
#500
0)
#550
b100101 !
b100101 <
b100101 ("
b1001 B
b1001 n
b1001 )"
b1001 y
b0 C
b0 o
b0 *"
b0 z
b1101 D
b1101 p
b1101 +"
b1101 {
b10 F
b10 #"
b1 =
b1 h
b1 '"
b1 0"
b0 >
b0 i
b0 &"
b0 /"
b1 ?
b1 j
b1 %"
b1 ."
b100 ^
b10 A
b10 _
1)
#600
0)
#650
b110110 !
b110110 <
b110110 ("
b0 B
b0 n
b0 )"
b0 y
b1011 C
b1011 o
b1011 *"
b1011 z
b11110 E
b11110 q
b11110 ,"
b11110 |
b101 ^
b0 =
b0 h
b0 '"
b0 0"
b1 >
b1 i
b1 &"
b1 /"
b10 @
b10 k
b10 $"
b10 -"
1)
#700
0)
#750
b1001100 !
b1001100 <
b1001100 ("
b1001 B
b1001 n
b1001 )"
b1001 y
b11010 D
b11010 p
b11010 +"
b11010 {
b11 F
b11 #"
b1 =
b1 h
b1 '"
b1 0"
b10 ?
b10 j
b10 %"
b10 ."
b110 ^
b11 A
b11 _
1)
#800
0)
#850
b1100110 !
b1100110 <
b1100110 ("
b10110 C
b10110 o
b10110 *"
b10110 z
b101101 E
b101101 q
b101101 ,"
b101101 |
b111 ^
b10 >
b10 i
b10 &"
b10 /"
b11 @
b11 k
b11 $"
b11 -"
1)
#900
0)
#950
b1111100 !
b1111100 <
b1111100 ("
b10010 B
b10010 n
b10010 )"
b10010 y
b100111 D
b100111 p
b100111 +"
b100111 {
b100 F
b100 #"
b10 =
b10 h
b10 '"
b10 0"
b11 ?
b11 j
b11 %"
b11 ."
b1000 ^
b100 A
b100 _
1)
#1000
0)
#1050
b10010110 !
b10010110 <
b10010110 ("
b100001 C
b100001 o
b100001 *"
b100001 z
b111100 E
b111100 q
b111100 ,"
b111100 |
b1001 ^
b11 >
b11 i
b11 &"
b11 /"
b100 @
b100 k
b100 $"
b100 -"
1)
#1100
0)
#1150
b10101100 !
b10101100 <
b10101100 ("
b11011 B
b11011 n
b11011 )"
b11011 y
b110100 D
b110100 p
b110100 +"
b110100 {
b111 F
b111 #"
b11 =
b11 h
b11 '"
b11 0"
b100 ?
b100 j
b100 %"
b100 ."
b1010 ^
b111 A
b111 _
1)
#1200
0)
#1250
b11100100 !
b11100100 <
b11100100 ("
b101100 C
b101100 o
b101100 *"
b101100 z
b1101001 E
b1101001 q
b1101001 ,"
b1101001 |
b1011 ^
b100 >
b100 i
b100 &"
b100 /"
b111 @
b111 k
b111 $"
b111 -"
1)
#1300
0)
#1350
b100010100 !
b100010100 <
b100010100 ("
b100100 B
b100100 n
b100100 )"
b100100 y
b1011011 D
b1011011 p
b1011011 +"
b1011011 {
b1 F
b1 #"
b100 =
b100 h
b100 '"
b100 0"
b111 ?
b111 j
b111 %"
b111 ."
b0 ^
1$
0%
b0 A
b0 _
1)
#1400
0)
#1450
b11011011 !
b11011011 <
b11011011 ("
b1001101 C
b1001101 o
b1001101 *"
b1001101 z
b1111 E
b1111 q
b1111 ,"
b1111 |
0$
b111 >
b111 i
b111 &"
b111 /"
b1 @
b1 k
b1 $"
b1 -"
1L
1)
#1460
1J
b1 G
b1 r
b1111 l
b11011010 !
b11011010 <
b11011010 ("
1v
b1 d
12
b1110 E
b1110 q
b1110 ,"
#1500
0)
#1550
b10100111 !
b10100111 <
b10100111 ("
b111111 B
b111111 n
b111111 )"
b111111 y
b1101 D
b1101 p
b1101 +"
b1101 {
b0 F
b0 #"
b1 "
b1 6
b1 Q
1#
1N
0L
b111 =
b111 h
b111 '"
b111 0"
b1 ?
b1 j
b1 %"
b1 ."
1%
b1 ^
1)
#1560
02
#1600
0)
#1650
0J
b0 G
b0 r
b1010111 !
b1010111 <
b1010111 ("
b0 l
0v
b0 d
b1 F
b1 #"
b1011 C
b1011 o
b1011 *"
b1011 z
b0 E
b0 q
b0 ,"
b0 |
b10 ^
b1 A
b1 _
b1 >
b1 i
b1 &"
b1 /"
b0 @
b0 k
b0 $"
b0 -"
1)
#1700
0)
#1750
1J
b1 G
b1 r
b1111 l
b100010 !
b100010 <
b100010 ("
1v
b1 d
b1001 B
b1001 n
b1001 )"
b1001 y
b0 D
b0 p
b0 +"
b0 {
b1110 E
b1110 q
b1110 ,"
b1111 |
b1 =
b1 h
b1 '"
b1 0"
b0 ?
b0 j
b0 %"
b0 ."
b1 @
b1 k
b1 $"
b1 -"
b11 ^
1)
#1800
0)
#1850
b100100 !
b100100 <
b100100 ("
b10 F
b10 #"
b0 C
b0 o
b0 *"
b0 z
b1101 D
b1101 p
b1101 +"
b1101 {
b100 ^
b10 A
b10 _
b0 >
b0 i
b0 &"
b0 /"
b1 ?
b1 j
b1 %"
b1 ."
1)
#1900
0)
#1950
0J
b0 G
b0 r
b110110 !
b110110 <
b110110 ("
b0 l
0v
b0 d
b0 B
b0 n
b0 )"
b0 y
b1011 C
b1011 o
b1011 *"
b1011 z
b11110 E
b11110 q
b11110 ,"
b11110 |
b0 =
b0 h
b0 '"
b0 0"
b1 >
b1 i
b1 &"
b1 /"
b10 @
b10 k
b10 $"
b10 -"
b101 ^
1)
#2000
0)
#2050
b1001100 !
b1001100 <
b1001100 ("
b11 F
b11 #"
b1001 B
b1001 n
b1001 )"
b1001 y
b11010 D
b11010 p
b11010 +"
b11010 {
b110 ^
b11 A
b11 _
b1 =
b1 h
b1 '"
b1 0"
b10 ?
b10 j
b10 %"
b10 ."
1)
#2100
0)
#2150
1J
b1 G
b1 r
b101101 l
b1100101 !
b1100101 <
b1100101 ("
1v
b1 d
b10110 C
b10110 o
b10110 *"
b10110 z
b101100 E
b101100 q
b101100 ,"
b101101 |
b10 >
b10 i
b10 &"
b10 /"
b11 @
b11 k
b11 $"
b11 -"
b111 ^
1)
#2200
0)
#2250
b1111011 !
b1111011 <
b1111011 ("
b100 F
b100 #"
b10010 B
b10010 n
b10010 )"
b10010 y
b100111 D
b100111 p
b100111 +"
b100111 {
b1000 ^
b100 A
b100 _
b10 =
b10 h
b10 '"
b10 0"
b11 ?
b11 j
b11 %"
b11 ."
1)
#2300
0)
#2350
0J
b0 G
b0 r
b10010110 !
b10010110 <
b10010110 ("
b0 l
0v
b0 d
b100001 C
b100001 o
b100001 *"
b100001 z
b111100 E
b111100 q
b111100 ,"
b111100 |
b11 >
b11 i
b11 &"
b11 /"
b100 @
b100 k
b100 $"
b100 -"
b1001 ^
1)
#2400
0)
#2450
b10101100 !
b10101100 <
b10101100 ("
b111 F
b111 #"
b11011 B
b11011 n
b11011 )"
b11011 y
b110100 D
b110100 p
b110100 +"
b110100 {
b1010 ^
b111 A
b111 _
b11 =
b11 h
b11 '"
b11 0"
b100 ?
b100 j
b100 %"
b100 ."
1)
#2500
0)
#2550
1J
b1 G
b1 r
b1101001 l
b11100011 !
b11100011 <
b11100011 ("
1v
b1 d
b101100 C
b101100 o
b101100 *"
b101100 z
b1101000 E
b1101000 q
b1101000 ,"
b1101001 |
b100 >
b100 i
b100 &"
b100 /"
b111 @
b111 k
b111 $"
b111 -"
b1011 ^
1)
#2600
0)
#2650
b100010011 !
b100010011 <
b100010011 ("
b1 F
b1 #"
b100100 B
b100100 n
b100100 )"
b100100 y
b1011011 D
b1011011 p
b1011011 +"
b1011011 {
b0 ^
1$
0%
b0 A
b0 _
b100 =
b100 h
b100 '"
b100 0"
b111 ?
b111 j
b111 %"
b111 ."
1)
#2660
0J
b0 G
b0 r
b0 l
b100010100 !
b100010100 <
b100010100 ("
0v
b0 d
b1101001 E
b1101001 q
b1101001 ,"
#2700
0)
#2750
b11011011 !
b11011011 <
b11011011 ("
b1001101 C
b1001101 o
b1001101 *"
b1001101 z
b1111 E
b1111 q
b1111 ,"
b1111 |
1L
b111 >
b111 i
b111 &"
b111 /"
b1 @
b1 k
b1 $"
b1 -"
0$
1)
