final_results/verification/diagnostic_controller.v
`timescale 1ns/1ns

module diagnostic_controller(

    input clk,
    input rst,
    input start_diag,

    output reg [3:0] test_x,
    output reg diag_busy,
    output reg diag_done

);

reg [3:0] state;

localparam IDLE      = 4'd0;
localparam TEST1     = 4'd1;
localparam WAIT1     = 4'd2;
localparam TEST2     = 4'd3;
localparam WAIT2     = 4'd4;
localparam TEST3     = 4'd5;
localparam WAIT3     = 4'd6;
localparam TEST4     = 4'd7;
localparam WAIT4     = 4'd8;
localparam TEST5     = 4'd9;
localparam WAIT5     = 4'd10;
localparam DONE      = 4'd11;


always @(posedge clk) begin

    if (rst) begin

        state <= IDLE;

        test_x <= 4'd0;

        diag_busy <= 1'b0;
        diag_done <= 1'b0;

    end

    else begin

        diag_done <= 1'b0;

        case (state)

            IDLE: begin

                test_x <= 4'd0;
                diag_busy <= 1'b0;

                if (start_diag) begin

                    state <= TEST1;
                    diag_busy <= 1'b1;

                end

            end


            TEST1: begin

                test_x <= 4'd1;

                state <= WAIT1;

            end


            WAIT1: begin

                test_x <= 4'd1;

                state <= TEST2;

            end


            TEST2: begin

                test_x <= 4'd2;

                state <= WAIT2;

            end


            WAIT2: begin

                test_x <= 4'd2;

                state <= TEST3;

            end


            TEST3: begin

                test_x <= 4'd3;

                state <= WAIT3;

            end


            WAIT3: begin

                test_x <= 4'd3;

                state <= TEST4;

            end


            TEST4: begin

                test_x <= 4'd4;

                state <= WAIT4;

            end


            WAIT4: begin

                test_x <= 4'd4;

                state <= TEST5;

            end


            TEST5: begin

                test_x <= 4'd7;

                state <= WAIT5;

            end


            WAIT5: begin

                test_x <= 4'd7;

                state <= DONE;

            end


            DONE: begin

                test_x <= 4'd0;

                diag_busy <= 1'b0;
                diag_done <= 1'b1;

                state <= IDLE;

            end


            default: begin

                state <= IDLE;

                test_x <= 4'd0;

                diag_busy <= 1'b0;
                diag_done <= 1'b0;

            end

        endcase

    end

end

endmodule

final_results/verification/diagnostic_controller_tb.v
`timescale 1ns/1ns

module diagnostic_controller_tb;

reg clk;
reg rst;
reg start_diag;

wire [3:0] test_x;
wire diag_busy;
wire diag_done;


diagnostic_controller dut(

    .clk(clk),
    .rst(rst),
    .start_diag(start_diag),

    .test_x(test_x),
    .diag_busy(diag_busy),
    .diag_done(diag_done)

);


initial begin

    clk = 0;

    forever #50 clk = ~clk;

end


initial begin

    $dumpfile("simulation/diagnostic_controller.vcd");
    $dumpvars(0, diagnostic_controller_tb);

    rst = 1;
    start_diag = 0;

    #100;

    rst = 0;

    #100;

    start_diag = 1;

    #100;

    start_diag = 0;

    #1200;

    $display("");
    $display("========================================");
    $display(" DIAGNOSTIC CONTROLLER TEST");
    $display("========================================");

    $display("test_x = %d", test_x);
    $display("diag_busy = %b", diag_busy);
    $display("diag_done = %b", diag_done);

    $display("========================================");

    $finish;

end


always @(posedge clk) begin

    $display("Time=%0t | test_x=%d | busy=%b | done=%b",
             $time,
             test_x,
             diag_busy,
             diag_done);

end

endmodule

simulation/diagnostic_controller.vcd
$date
	Thu Sep 17 01:35:54 2026
$end
$version
	Icarus Verilog
$end
$timescale
	1ns
$end
$scope module diagnostic_controller_tb $end
$var wire 4 ! test_x [3:0] $end
$var wire 1 " diag_done $end
$var wire 1 # diag_busy $end
$var reg 1 $ clk $end
$var reg 1 % rst $end
$var reg 1 & start_diag $end
$scope module dut $end
$var wire 1 $ clk $end
$var wire 1 % rst $end
$var wire 1 & start_diag $end
$var parameter 4 ' DONE $end
$var parameter 4 ( IDLE $end
$var parameter 4 ) TEST1 $end
$var parameter 4 * TEST2 $end
$var parameter 4 + TEST3 $end
$var parameter 4 , TEST4 $end
$var parameter 4 - TEST5 $end
$var parameter 4 . WAIT1 $end
$var parameter 4 / WAIT2 $end
$var parameter 4 0 WAIT3 $end
$var parameter 4 1 WAIT4 $end
$var parameter 4 2 WAIT5 $end
$var reg 1 # diag_busy $end
$var reg 1 " diag_done $end
$var reg 4 3 state [3:0] $end
$var reg 4 4 test_x [3:0] $end
$upscope $end
$upscope $end
$enddefinitions $end
$comment Show the parameter values. $end
$dumpall
b1010 2
b1000 1
b110 0
b100 /
b10 .
b1001 -
b111 ,
b101 +
b11 *
b1 )
b0 (
b1011 '
$end
#0
$dumpvars
bx 4
bx 3
0&
1%
0$
x#
x"
bx !
$end
#50
0"
0#
b0 !
b0 4
b0 3
1$
#100
0$
0%
#150
1$
#200
0$
1&
#250
1#
b1 3
1$
#300
0$
0&
#350
b10 3
b1 !
b1 4
1$
#400
0$
#450
b11 3
1$
#500
0$
#550
b100 3
b10 !
b10 4
1$
#600
0$
#650
b101 3
1$
#700
0$
#750
b110 3
b11 !
b11 4
1$
#800
0$
#850
b111 3
1$
#900
0$
#950
b1000 3
b100 !
b100 4
1$
#1000
0$
#1050
b1001 3
1$
#1100
0$
#1150
b1010 3
b111 !
b111 4
1$
#1200
0$
#1250
b1011 3
1$
#1300
0$
#1350
b0 3
1"
0#
b0 !
b0 4
1$
#1400
0$
#1450
0"
1$
