final_results/verification/fir_diagnostic.v
`timescale 1ns/1ns

module fir_diagnostic(

    input [3:0] h0,
    input [3:0] h1,
    input [3:0] h2,
    input [3:0] h3,

    input [3:0] x0,
    input [3:0] x1,
    input [3:0] x2,
    input [3:0] x3,

    input [7:0] p0,
    input [7:0] p1,
    input [7:0] p2,
    input [7:0] p3,

    output fault_p0,
    output fault_p1,
    output fault_p2,
    output fault_p3,

    output [3:0] fault_vector,

    output fault_detected,
    output [1:0] fault_location,
    output [2:0] fault_bit,
    output fault_type

);

wire [7:0] expected_p0;
wire [7:0] expected_p1;
wire [7:0] expected_p2;
wire [7:0] expected_p3;

wire [7:0] mismatch_p0;
wire [7:0] mismatch_p1;
wire [7:0] mismatch_p2;
wire [7:0] mismatch_p3;

wire [7:0] selected_expected;
wire selected_actual;


assign expected_p0 = h0 * x0;
assign expected_p1 = h1 * x1;
assign expected_p2 = h2 * x2;
assign expected_p3 = h3 * x3;


assign mismatch_p0 = expected_p0 ^ p0;
assign mismatch_p1 = expected_p1 ^ p1;
assign mismatch_p2 = expected_p2 ^ p2;
assign mismatch_p3 = expected_p3 ^ p3;


assign fault_p0 = |mismatch_p0;
assign fault_p1 = |mismatch_p1;
assign fault_p2 = |mismatch_p2;
assign fault_p3 = |mismatch_p3;


assign fault_vector = {
    fault_p3,
    fault_p2,
    fault_p1,
    fault_p0
};


assign fault_detected =
        fault_p0 |
        fault_p1 |
        fault_p2 |
        fault_p3;


assign fault_location =
        fault_p0 ? 2'b00 :
        fault_p1 ? 2'b01 :
        fault_p2 ? 2'b10 :
        fault_p3 ? 2'b11 :
                   2'b00;


assign fault_bit =
        fault_p0 ? (
            mismatch_p0[0] ? 3'd0 :
            mismatch_p0[1] ? 3'd1 :
            mismatch_p0[2] ? 3'd2 :
            mismatch_p0[3] ? 3'd3 :
            mismatch_p0[4] ? 3'd4 :
            mismatch_p0[5] ? 3'd5 :
            mismatch_p0[6] ? 3'd6 :
            mismatch_p0[7] ? 3'd7 :
            3'd0
        ) :
        fault_p1 ? (
            mismatch_p1[0] ? 3'd0 :
            mismatch_p1[1] ? 3'd1 :
            mismatch_p1[2] ? 3'd2 :
            mismatch_p1[3] ? 3'd3 :
            mismatch_p1[4] ? 3'd4 :
            mismatch_p1[5] ? 3'd5 :
            mismatch_p1[6] ? 3'd6 :
            mismatch_p1[7] ? 3'd7 :
            3'd0
        ) :
        fault_p2 ? (
            mismatch_p2[0] ? 3'd0 :
            mismatch_p2[1] ? 3'd1 :
            mismatch_p2[2] ? 3'd2 :
            mismatch_p2[3] ? 3'd3 :
            mismatch_p2[4] ? 3'd4 :
            mismatch_p2[5] ? 3'd5 :
            mismatch_p2[6] ? 3'd6 :
            mismatch_p2[7] ? 3'd7 :
            3'd0
        ) :
        fault_p3 ? (
            mismatch_p3[0] ? 3'd0 :
            mismatch_p3[1] ? 3'd1 :
            mismatch_p3[2] ? 3'd2 :
            mismatch_p3[3] ? 3'd3 :
            mismatch_p3[4] ? 3'd4 :
            mismatch_p3[5] ? 3'd5 :
            mismatch_p3[6] ? 3'd6 :
            mismatch_p3[7] ? 3'd7 :
            3'd0
        ) :
        3'd0;


assign selected_expected =
        fault_p0 ? expected_p0 :
        fault_p1 ? expected_p1 :
        fault_p2 ? expected_p2 :
        fault_p3 ? expected_p3 :
        8'd0;


assign selected_actual =
        fault_p0 ? p0[fault_bit] :
        fault_p1 ? p1[fault_bit] :
        fault_p2 ? p2[fault_bit] :
        fault_p3 ? p3[fault_bit] :
        1'b0;


assign fault_type =
        fault_detected ?
        ((selected_expected[fault_bit] == 1'b0) &&
         (selected_actual == 1'b1)) :
        1'b0;

endmodule

faults/fir_faulty.v
`timescale 1ns/1ns

module fir(
    x, h0, h1, h2, h3, y, rst, clk
);

input [3:0] x;
input rst, clk;
input [3:0] h0, h1, h2, h3;

output [9:0] y;

reg [3:0] x0, x1, x2, x3;

wire [7:0] p0, p1, p2, p3;

assign p0 = 8'd0;
assign p1 = h1 * x1;
assign p2 = h2 * x2;
assign p3 = h3 * x3;

always @(posedge clk) begin
    if (rst) begin
        x0 <= 4'd0;
        x1 <= 4'd0;
        x2 <= 4'd0;
        x3 <= 4'd0;
    end
    else begin
        x0 <= x;
        x1 <= x0;
        x2 <= x1;
        x3 <= x2;
    end
end

assign y = p0 + p1 + p2 + p3;

endmodule

tb/fir_tb.v
module fir_tb;

reg [3:0] x;
reg rst, clk;
reg [3:0] h0, h1, h2, h3;

wire [9:0] y;

wire [7:0] p0, p1, p2, p3;
wire [3:0] x0, x1, x2, x3;

wire fault_p0;
wire fault_p1;
wire fault_p2;
wire fault_p3;

wire fault_detected;
wire [1:0] fault_location;
wire [1:0] fault_type;

wire [7:0] expected_p0;
wire [7:0] expected_p1;
wire [7:0] expected_p2;
wire [7:0] expected_p3;

fir f1(
    x, h0, h1, h2, h3, y, rst, clk
);

assign x0 = f1.x0;
assign x1 = f1.x1;
assign x2 = f1.x2;
assign x3 = f1.x3;

assign p0 = f1.p0;
assign p1 = f1.p1;
assign p2 = f1.p2;
assign p3 = f1.p3;

assign expected_p0 = h0 * x0;
assign expected_p1 = h1 * x1;
assign expected_p2 = h2 * x2;
assign expected_p3 = h3 * x3;

fir_diagnostic d1(
    .h0(h0),
    .h1(h1),
    .h2(h2),
    .h3(h3),

    .x0(x0),
    .x1(x1),
    .x2(x2),
    .x3(x3),

    .p0(p0),
    .p1(p1),
    .p2(p2),
    .p3(p3),

    .fault_p0(fault_p0),
    .fault_p1(fault_p1),
    .fault_p2(fault_p2),
    .fault_p3(fault_p3),

    .fault_detected(fault_detected),
    .fault_location(fault_location),
    .fault_type(fault_type)
);

initial begin
    clk = 0;
    forever #50 clk = ~clk;
end

initial begin
    $dumpfile("simulation/fir.vcd");
    $dumpvars(0, fir_tb);

    h0 = 4'd1;
    h1 = 4'd2;
    h2 = 4'd2;
    h3 = 4'd1;

    rst = 1;
    x = 4'd0;

    #100;
    rst = 0;

    #25 x = 4'd1;
    #100 x = 4'd2;
    #100 x = 4'd3;
    #100 x = 4'd4;

    #200;
    $finish;
end

initial begin
    $monitor("Time=%0t | x=%d | p0=%d F0=%b | p1=%d F1=%b | p2=%d F2=%b | p3=%d F3=%b | DET=%b | LOC=%b | TYPE=%b | y=%d",
             $time,
             x,
             p0, fault_p0,
             p1, fault_p1,
             p2, fault_p2,
             p3, fault_p3,
             fault_detected,
             fault_location,
             fault_type,
             y);
end

endmodule

simulation/fir.vcd
$date
	Sat Sep 19 15:10:15 2026
$end
$version
	Icarus Verilog
$end
$timescale
	1ns
$end
$scope module fir_tb $end
$var wire 8 ! p0 [7:0] $end
$var wire 8 " p1 [7:0] $end
$var wire 8 # p2 [7:0] $end
$var wire 8 $ p3 [7:0] $end
$var wire 4 % x1 [3:0] $end
$var wire 4 & x2 [3:0] $end
$var wire 4 ' x3 [3:0] $end
$var wire 10 ( y [9:0] $end
$var wire 4 ) x0 [3:0] $end
$var wire 2 * fault_type [1:0] $end
$var wire 1 + fault_p3 $end
$var wire 1 , fault_p2 $end
$var wire 1 - fault_p1 $end
$var wire 1 . fault_p0 $end
$var wire 2 / fault_location [1:0] $end
$var wire 1 0 fault_detected $end
$var wire 8 1 expected_p3 [7:0] $end
$var wire 8 2 expected_p2 [7:0] $end
$var wire 8 3 expected_p1 [7:0] $end
$var wire 8 4 expected_p0 [7:0] $end
$var reg 1 5 clk $end
$var reg 4 6 h0 [3:0] $end
$var reg 4 7 h1 [3:0] $end
$var reg 4 8 h2 [3:0] $end
$var reg 4 9 h3 [3:0] $end
$var reg 1 : rst $end
$var reg 4 ; x [3:0] $end
$scope module d1 $end
$var wire 1 0 fault_detected $end
$var wire 4 < h0 [3:0] $end
$var wire 4 = h1 [3:0] $end
$var wire 4 > h2 [3:0] $end
$var wire 4 ? h3 [3:0] $end
$var wire 8 @ mismatch_p0 [7:0] $end
$var wire 8 A mismatch_p1 [7:0] $end
$var wire 8 B mismatch_p2 [7:0] $end
$var wire 8 C mismatch_p3 [7:0] $end
$var wire 8 D p0 [7:0] $end
$var wire 8 E p1 [7:0] $end
$var wire 8 F p2 [7:0] $end
$var wire 8 G p3 [7:0] $end
$var wire 4 H x1 [3:0] $end
$var wire 4 I x2 [3:0] $end
$var wire 4 J x3 [3:0] $end
$var wire 4 K x0 [3:0] $end
$var wire 8 L selected_expected [7:0] $end
$var wire 1 M selected_actual $end
$var wire 4 N fault_vector [3:0] $end
$var wire 1 O fault_type $end
$var wire 1 + fault_p3 $end
$var wire 1 , fault_p2 $end
$var wire 1 - fault_p1 $end
$var wire 1 . fault_p0 $end
$var wire 2 P fault_location [1:0] $end
$var wire 3 Q fault_bit [2:0] $end
$var wire 8 R expected_p3 [7:0] $end
$var wire 8 S expected_p2 [7:0] $end
$var wire 8 T expected_p1 [7:0] $end
$var wire 8 U expected_p0 [7:0] $end
$upscope $end
$scope module f1 $end
$var wire 1 5 clk $end
$var wire 4 V h0 [3:0] $end
$var wire 4 W h1 [3:0] $end
$var wire 4 X h2 [3:0] $end
$var wire 4 Y h3 [3:0] $end
$var wire 8 Z p0 [7:0] $end
$var wire 1 : rst $end
$var wire 4 [ x [3:0] $end
$var wire 10 \ y [9:0] $end
$var wire 8 ] p3 [7:0] $end
$var wire 8 ^ p2 [7:0] $end
$var wire 8 _ p1 [7:0] $end
$var reg 4 ` x0 [3:0] $end
$var reg 4 a x1 [3:0] $end
$var reg 4 b x2 [3:0] $end
$var reg 4 c x3 [3:0] $end
$upscope $end
$upscope $end
$enddefinitions $end
$comment Show the parameter values. $end
$dumpall
$end
#0
$dumpvars
bx c
bx b
bx a
bx `
bx _
bx ^
bx ]
bx \
b0 [
b0 Z
b1 Y
b10 X
b10 W
b1 V
bx U
bx T
bx S
bx R
bx Q
bx P
xO
bx N
xM
bx L
bx K
bx J
bx I
bx H
bx G
bx F
bx E
b0 D
bx C
bx B
bx A
bx @
b1 ?
b10 >
b10 =
b1 <
b0 ;
1:
b1 9
b10 8
b10 7
b1 6
05
bx 4
bx 3
bx 2
bx 1
x0
bx /
x.
x-
x,
x+
b0x *
bx )
bx (
bx '
bx &
bx %
bx $
bx #
bx "
b0 !
$end
#50
b0 /
b0 P
b0 Q
0M
b0 L
b0 *
0O
00
b0 N
b0 (
b0 \
0+
b0 C
0,
b0 B
0-
b0 A
0.
b0 @
b0 $
b0 G
b0 ]
b0 1
b0 R
b0 #
b0 F
b0 ^
b0 2
b0 S
b0 "
b0 E
b0 _
b0 3
b0 T
b0 U
b0 4
b0 '
b0 J
b0 c
b0 &
b0 I
b0 b
b0 %
b0 H
b0 a
b0 )
b0 K
b0 `
15
#100
05
0:
#125
b1 ;
b1 [
#150
10
b1 N
b1 L
1.
b1 @
b1 U
b1 4
b1 )
b1 K
b1 `
15
#200
05
#225
b10 ;
b10 [
#250
b1 Q
b10 (
b10 \
b10 L
b10 @
b10 "
b10 E
b10 _
b10 3
b10 T
b10 U
b10 4
b1 %
b1 H
b1 a
b10 )
b10 K
b10 `
15
#300
05
#325
b11 ;
b11 [
#350
b0 Q
b110 (
b110 \
b11 L
b11 @
b10 #
b10 F
b10 ^
b10 2
b10 S
b100 "
b100 E
b100 _
b100 3
b100 T
b11 U
b11 4
b1 &
b1 I
b1 b
b10 %
b10 H
b10 a
b11 )
b11 K
b11 `
15
#400
05
#425
b100 ;
b100 [
#450
b10 Q
b1011 (
b1011 \
b100 L
b100 @
b1 $
b1 G
b1 ]
b1 1
b1 R
b100 #
b100 F
b100 ^
b100 2
b100 S
b110 "
b110 E
b110 _
b110 3
b110 T
b100 U
b100 4
b1 '
b1 J
b1 c
b10 &
b10 I
b10 b
b11 %
b11 H
b11 a
b100 )
b100 K
b100 `
15
#500
05
#550
b10000 (
b10000 \
b10 $
b10 G
b10 ]
b10 1
b10 R
b110 #
b110 F
b110 ^
b110 2
b110 S
b1000 "
b1000 E
b1000 _
b1000 3
b1000 T
b10 '
b10 J
b10 c
b11 &
b11 I
b11 b
b100 %
b100 H
b100 a
15
